{"nodes": [{"id": "vite_config", "label": "vite.config.js", "file_type": "code", "source_file": "client/vite.config.js", "source_location": null, "source_url": null, "captured_at": null, "author": null, "contributor": null}, {"id": "vite_config_proxy_config", "label": "Vite Dev Proxy Config", "file_type": "code", "source_file": "client/vite.config.js", "source_location": null, "source_url": null, "captured_at": null, "author": null, "contributor": null, "rationale": "Proxies /api requests to http://localhost:3000 during development, integrating with a backend API server running on port 3000."}, {"id": "vite_config_alias_config", "label": "Vite Alias Config", "file_type": "code", "source_file": "client/vite.config.js", "source_location": null, "source_url": null, "captured_at": null, "author": null, "contributor": null}], "edges": [{"source": "vite_config_proxy_config", "target": "package_json", "relation": "conceptually_related_to", "confidence": "INFERRED", "confidence_score": 0.8, "source_file": "client/vite.config.js", "source_location": null, "weight": 1.0}, {"source": "vite_config_alias_config", "target": "tsconfig_app", "relation": "conceptually_related_to", "confidence": "INFERRED", "confidence_score": 0.85, "source_file": "client/vite.config.js", "source_location": null, "weight": 1.0}], "hyperedges": [{"id": "alias_configuration", "label": "@ Alias Configuration", "nodes": ["tsconfig_app", "vite_config", "vite_config_alias_config"], "relation": "implement", "confidence": "INFERRED", "confidence_score": 0.85, "source_file": "client/vite.config.js"}]}