{"nodes": [{"id": "routes_admin_adminroutes", "label": "Admin Routes", "file_type": "code", "source_file": "server/src/routes/admin.ts", "source_location": null, "source_url": null, "captured_at": null, "author": null, "contributor": null}], "edges": [{"source": "routes_admin_adminroutes", "target": "utils_token_service_granttokens", "relation": "calls", "confidence": "INFERRED", "confidence_score": 0.85, "source_file": "server/src/routes/admin.ts", "source_location": null, "weight": 1.0}, {"source": "routes_admin_adminroutes", "target": "middleware_auth_authmiddleware", "relation": "calls", "confidence": "INFERRED", "confidence_score": 0.85, "source_file": "server/src/routes/admin.ts", "source_location": null, "weight": 1.0}, {"source": "routes_admin_adminroutes", "target": "middleware_auth_adminguard", "relation": "calls", "confidence": "INFERRED", "confidence_score": 0.85, "source_file": "server/src/routes/admin.ts", "source_location": null, "weight": 1.0}], "hyperedges": []}