{"nodes": [{"id": "bridges_kiro_process_manager_kiroprocessmanager", "label": "KiroProcessManager", "file_type": "code", "source_file": "server/src/bridges/kiro-process-manager.ts", "source_location": null, "source_url": null, "captured_at": null, "author": null, "contributor": null, "rationale": "Spawns kiro-cli via sudo runuser for privilege separation. Uses --resume to continue the most recent session in the directory. Creates and chowns directory before file watcher starts."}, {"id": "bridges_kiro_process_manager_escapeforsinglequotes", "label": "escapeForSingleQuotes", "file_type": "code", "source_file": "server/src/bridges/kiro-process-manager.ts", "source_location": null, "source_url": null, "captured_at": null, "author": null, "contributor": null}], "edges": [{"source": "bridges_kiro_process_manager_kiroprocessmanager", "target": "bridges_kiro_process_manager_escapeforsinglequotes", "relation": "calls", "confidence": "EXTRACTED", "confidence_score": 1.0, "source_file": "server/src/bridges/kiro-process-manager.ts", "source_location": null, "weight": 1.0}], "hyperedges": []}